filetxt/__init__.py
filetxt/loader.py
filetxt/sentences.py
filetxt/version.py
filetxt-0.0.2.dist-info/METADATA
filetxt-0.0.2.dist-info/WHEEL
filetxt-0.0.2.dist-info/top_level.txt
filetxt-0.0.2.dist-info/RECORD
