Metadata-Version: 2.4
Name: filetxt
Version: 0.0.2
Summary: a document tools for loading document from file and split sentences
Author: "yu moqing"
Author-email: "yumoqing@gmail.com"
License: "MIT"
Requires-Dist: spacy
Requires-Dist: langchain_community
Requires-Dist: pillow
Requires-Dist: mobi
Requires-Dist: html2text
Requires-Dist: python-docx
Requires-Dist: python-pptx
Requires-Dist: openpyxl
Requires-Dist: pypdf
Requires-Dist: ebooklib
Requires-Dist: beautifulsoup4
